prcssr/Controller.py
prcssr/__init__.py
prcssr/__main__.py
prcssr/model/Processor.py
prcssr/model/__init__.py
prcssr-1.0.0.dist-info/LICENSE.md
prcssr-1.0.0.dist-info/METADATA
prcssr-1.0.0.dist-info/WHEEL
prcssr-1.0.0.dist-info/entry_points.txt
prcssr-1.0.0.dist-info/top_level.txt
prcssr-1.0.0.dist-info/RECORD
