Metadata-Version: 2.1
Name: prcssr
Version: 1.0.0
Summary: Command Execution with Logging
Home-page: https://github.com/5f0ne/prcssr
Author: 5f0
License: MIT
Classifier: Operating System :: OS Independent 
Classifier: Programming Language :: Python :: 3.5 
Classifier: License :: OSI Approved :: MIT License 
License-File: LICENSE.md
